wt_django_templatetags-1.1.0.dist-info/licenses/LICENSE
wt_templatetags/__init__.py
wt_templatetags/_version.py
wt_templatetags/settings.py
wt_templatetags/templatetags/__init__.py
wt_templatetags/templatetags/pagination_tags.py
wt_templatetags/templatetags/static_tags.py
wt_django_templatetags-1.1.0.dist-info/METADATA
wt_django_templatetags-1.1.0.dist-info/WHEEL
wt_django_templatetags-1.1.0.dist-info/top_level.txt
wt_django_templatetags-1.1.0.dist-info/RECORD
